yuanian/__init__.py
yuanian/version-config.yaml
yuanian-0.0.1.dist-info/LICENSE
yuanian-0.0.1.dist-info/METADATA
yuanian-0.0.1.dist-info/WHEEL
yuanian-0.0.1.dist-info/top_level.txt
yuanian-0.0.1.dist-info/RECORD
