Metadata-Version: 2.1
Name: yuanian
Version: 0.0.1
Summary: Animation engine for explanatory math videos
Home-page: https://github.com/beidongjiedeguang/yuanian
Author: kunyuan
Author-email: beidongjiedeguang@gmail.com
License: MIT
Keywords: Mathematics,Physics,Machine Learning,Neural Networks
Platform: UNKNOWN
Classifier: Operating System :: OS Independent
Classifier: Intended Audience :: Developers
Classifier: Intended Audience :: Science/Research
Classifier: Topic :: Scientific/Engineering :: Artificial Intelligence
Classifier: Programming Language :: Python :: 3
Classifier: Programming Language :: Python :: 3.8
Requires-Dist: sparrow-tool
